pathable/__init__.py
pathable/accessors.py
pathable/dataclasses.py
pathable/parsers.py
pathable/paths.py
pathable/py.typed
pathable/types.py
pathable-0.4.2.dist-info/LICENSE
pathable-0.4.2.dist-info/WHEEL
pathable-0.4.2.dist-info/METADATA
pathable-0.4.2.dist-info/RECORD
