Metadata-Version: 2.1
Name: pathable
Version: 0.4.2
Summary: Object-oriented paths
Home-page: https://github.com/p1c2u/pathable
License: Apache License, Version 2.0
Keywords: dict,dictionary,list,lookup,path,pathable
Author: Artur Maciag
Author-email: maciag.artur@gmail.com
Requires-Python: >=3.7.0,<4.0.0
Classifier: Development Status :: 4 - Beta
Classifier: Intended Audience :: Developers
Classifier: License :: Other/Proprietary License
Classifier: Operating System :: OS Independent
Classifier: Programming Language :: Python :: 3
Classifier: Programming Language :: Python :: 3.10
Classifier: Programming Language :: Python :: 3.7
Classifier: Programming Language :: Python :: 3.8
Classifier: Programming Language :: Python :: 3.9
Classifier: Topic :: Software Development :: Libraries
Classifier: Topic :: Software Development :: Libraries :: Python Modules
Provides-Extra: dev
Project-URL: Repository, https://github.com/p1c2u/pathable
